qpg/__init__.py
qpg/base.py
qpg/schemas.py
qpg/db/__init__.py
qpg/db/models.py
qpg/db/utils.py
qpg-0.0.4.dist-info/METADATA
qpg-0.0.4.dist-info/WHEEL
qpg-0.0.4.dist-info/top_level.txt
qpg-0.0.4.dist-info/RECORD
